ptrait/__init__.py
ptrait/exceptions.py
ptrait/trait.py
tests/__init__.py
tests/test_trait.py
tests/test_trait_param_required.py
ptrait-0.0.3.dist-info/LICENSE
ptrait-0.0.3.dist-info/METADATA
ptrait-0.0.3.dist-info/WHEEL
ptrait-0.0.3.dist-info/top_level.txt
ptrait-0.0.3.dist-info/RECORD
