Metadata-Version: 2.1
Name: ptrait
Version: 0.0.3
Summary: trait
Home-page: https://github.com/xyloon/ptrait
Author: xyloon
Author-email: xyloon@gmail.com
License: MIT
Platform: UNKNOWN
Classifier: Programming Language :: Python :: 3
Classifier: License :: OSI Approved :: MIT License
Classifier: Operating System :: OS Independent
